LICENSE
MANIFEST.in
README.md
setup.py
retries.egg-info/PKG-INFO
retries.egg-info/SOURCES.txt
retries.egg-info/dependency_links.txt
retries.egg-info/top_level.txt
retry/__init__.py