Metadata-Version: 1.1
Name: retries
Version: 1.0
Summary: Decorator for retrying exec a method
Home-page: https://github.com/soasme/retries
Author: soasme
Author-email: soasme@gmail.com
License: MIT License
Keywords: decorator decorators retry exception
Platform: UNKNOWN
Classifier: Development Status :: 4 - Beta
Classifier: Topic :: Utilities
Classifier: License :: OSI Approved :: MIT License
